WowMetaLogs-0.2.1.dist-info/METADATA
WowMetaLogs-0.2.1.dist-info/RECORD
WowMetaLogs-0.2.1.dist-info/WHEEL
WowMetaLogs-0.2.1.dist-info/top_level.txt
wowmetalogs/__init__.py
wowmetalogs/apis/__init__.py
wowmetalogs/apis/blizzapi.py
wowmetalogs/tests/__init__.py
wowmetalogs/tests/achievementstest.py
wowmetalogs/tests/samplefiles.py
wowmetalogs/warcraft/__init__.py
wowmetalogs/warcraft/achievement.py
wowmetalogs/warcraft/character.py
wowmetalogs/warcraft/guild.py
wowmetalogs/warcraft/item.py
