Metadata-Version: 2.1
Name: WowMetaLogs
Version: 0.2.1
Summary: Library for interfacing with the official Blizzard API and the WarcraftLogs API.
Home-page: UNKNOWN
Author: BKrenz
Author-email: UNKNOWN
License: UNKNOWN
Platform: UNKNOWN
